<?xml version="1.0" encoding="UTF-8" ?>
<!DOCTYPE component SYSTEM "../../etc/component-dependency.dtd" >

<component
    name="carrot2-filter-lingo-reloaded"
    description="Carrot2 Lingo Reloaded Clustering filter">

	<!-- Carrot2 components -->
	<dependency name="carrot2-util-common" />
    <dependency name="carrot2-util-matrix" />
    <dependency name="carrot2-util-tokenizer" />
	<dependency name="commons-primitives" />
	<dependency name="carrot2-local-core" />
    <dependency name="carrot2-license" />
    <dependency name="log4j" />
    
    <dependency name="junit" profile="test" />
    <dependency name="junit-addons" profile="test" />
</component>
