<component-suite>
  <include suite="carrot2-default/suite-common.xml" />

  <sources>
    <source component-class="org.carrot2.webapp.source.WebDocumentSource" id="web">
      <label>Web</label>
      <title>Search the Web with etools.ch</title>
      <description>Searches the web using the etools.ch meta search engine</description>
      <mnemonic>W</mnemonic>
      <example-queries>
        <example-query>data mining</example-query>
        <example-query>london</example-query>
        <example-query>clustering</example-query>
      </example-queries>
    </source>
    <source component-class="org.carrot2.source.boss.BossDocumentSource" id="put" attribute-sets-resource="/carrot2-default/put.attributes.xml" position="END">
      <label>PUT</label>
      <title>*.put.poznan.pl search (with Yahoo Boss)</title>
      <mnemonic>U</mnemonic>
      <description>Searches Poznan University of Technology domain using Yahoo Boss Web Search API</description>
      <icon-path>icons/put.gif</icon-path>
      <example-queries>
        <example-query>idss</example-query>
        <example-query>seminaria</example-query>
        <example-query>publikacje</example-query>
      </example-queries>
    </source>
    <source component-class="org.carrot2.source.opensearch.OpenSearchDocumentSource" id="icerocket" position="END">
      <label>Blogs</label>
      <title>Blogs from icerocket.com</title>
      <description>Searches blog content using the icerocket.com search engine</description>
      <mnemonic>B</mnemonic>
      <example-queries>
        <example-query>olympics</example-query>
        <example-query>music</example-query>
        <example-query>election</example-query>
      </example-queries>
    </source>
    <source id="lucene" 
        attribute-sets-resource="/carrot2-default/lucene.attributes.xml"
        component-class="org.carrot2.source.lucene.LuceneDocumentSource">
      <label>Lucene</label>
      <title>Lucene</title>
      <mnemonic>L</mnemonic>
      <description>Lucene search</description>
      <example-queries>
        <example-query>query1</example-query>
        <example-query>query2</example-query>
      </example-queries>
    </source>
  </sources>
</component-suite>
